[
    {
        "id": 101,
        "box_code": "6152705117874",
        "sequence": 7,
        "dimension": [
            480,
            380,
            340
        ]
    },
    {
        "id": 102,
        "box_code": "6089324934218",
        "sequence": 33,
        "dimension": [
            270,
            100,
            150
        ]
    },
    {
        "id": 103,
        "box_code": "3037275762438",
        "sequence": 10,
        "dimension": [
            340,
            350,
            210
        ]
    },
    {
        "id": 104,
        "box_code": "9164738435453",
        "sequence": 33,
        "dimension": [
            410,
            310,
            280
        ]
    },
    {
        "id": 105,
        "box_code": "3791096277761",
        "sequence": 25,
        "dimension": [
            340,
            350,
            210
        ]
    },
    {
        "id": 106,
        "box_code": "7834845343535",
        "sequence": 17,
        "dimension": [
            350,
            250,
            100
        ]
    },
    {
        "id": 107,
        "box_code": "2790866885170",
        "sequence": 27,
        "dimension": [
            270,
            100,
            150
        ]
    },
    {
        "id": 108,
        "box_code": "7071769994001",
        "sequence": 31,
        "dimension": [
            480,
            380,
            340
        ]
    },
    {
        "id": 109,
        "box_code": "9206514273985",
        "sequence": 6,
        "dimension": [
            270,
            100,
            150
        ]
    },
    {
        "id": 110,
        "box_code": "7380230241739",
        "sequence": 40,
        "dimension": [
            480,
            380,
            340
        ]
    },
    {
        "id": 111,
        "box_code": "3168895535053",
        "sequence": 17,
        "dimension": [
            480,
            380,
            340
        ]
    },
    {
        "id": 112,
        "box_code": "8066102146042",
        "sequence": 22,
        "dimension": [
            480,
            380,
            340
        ]
    },
    {
        "id": 113,
        "box_code": "7725202403929",
        "sequence": 38,
        "dimension": [
            480,
            380,
            340
        ]
    },
    {
        "id": 114,
        "box_code": "7602754191551",
        "sequence": 35,
        "dimension": [
            340,
            350,
            210
        ]
    },
    {
        "id": 115,
        "box_code": "8216236714476",
        "sequence": 25,
        "dimension": [
            480,
            380,
            340
        ]
    },
    {
        "id": 116,
        "box_code": "2097593734120",
        "sequence": 25,
        "dimension": [
            340,
            350,
            210
        ]
    },
    {
        "id": 117,
        "box_code": "4552225668546",
        "sequence": 35,
        "dimension": [
            270,
            100,
            150
        ]
    },
    {
        "id": 118,
        "box_code": "7184915383325",
        "sequence": 39,
        "dimension": [
            350,
            250,
            100
        ]
    },
    {
        "id": 119,
        "box_code": "4591882424761",
        "sequence": 16,
        "dimension": [
            270,
            100,
            150
        ]
    },
    {
        "id": 120,
        "box_code": "7909701019025",
        "sequence": 23,
        "dimension": [
            480,
            380,
            340
        ]
    },
    {
        "id": 121,
        "box_code": "8089776742945",
        "sequence": 36,
        "dimension": [
            340,
            350,
            210
        ]
    },
    {
        "id": 122,
        "box_code": "6631930196505",
        "sequence": 35,
        "dimension": [
            410,
            310,
            280
        ]
    },
    {
        "id": 123,
        "box_code": "7814770124949",
        "sequence": 16,
        "dimension": [
            410,
            310,
            280
        ]
    },
    {
        "id": 124,
        "box_code": "3203281480565",
        "sequence": 34,
        "dimension": [
            350,
            250,
            100
        ]
    },
    {
        "id": 125,
        "box_code": "4428958610938",
        "sequence": 5,
        "dimension": [
            270,
            100,
            150
        ]
    },
    {
        "id": 126,
        "box_code": "2116930011836",
        "sequence": 8,
        "dimension": [
            350,
            250,
            100
        ]
    },
    {
        "id": 127,
        "box_code": "6836894584149",
        "sequence": 16,
        "dimension": [
            340,
            350,
            210
        ]
    },
    {
        "id": 128,
        "box_code": "7685755365462",
        "sequence": 23,
        "dimension": [
            480,
            380,
            340
        ]
    },
    {
        "id": 129,
        "box_code": "3684247544526",
        "sequence": 25,
        "dimension": [
            350,
            250,
            100
        ]
    },
    {
        "id": 130,
        "box_code": "2973135389922",
        "sequence": 16,
        "dimension": [
            340,
            350,
            210
        ]
    },
    {
        "id": 131,
        "box_code": "9975054979778",
        "sequence": 14,
        "dimension": [
            350,
            250,
            100
        ]
    },
    {
        "id": 132,
        "box_code": "3386545439367",
        "sequence": 8,
        "dimension": [
            410,
            310,
            280
        ]
    },
    {
        "id": 133,
        "box_code": "9893681444346",
        "sequence": 7,
        "dimension": [
            350,
            250,
            100
        ]
    },
    {
        "id": 134,
        "box_code": "3411912649616",
        "sequence": 26,
        "dimension": [
            340,
            350,
            210
        ]
    },
    {
        "id": 135,
        "box_code": "9316695550804",
        "sequence": 25,
        "dimension": [
            340,
            350,
            210
        ]
    },
    {
        "id": 136,
        "box_code": "1214671786860",
        "sequence": 24,
        "dimension": [
            480,
            380,
            340
        ]
    },
    {
        "id": 137,
        "box_code": "2559175674206",
        "sequence": 38,
        "dimension": [
            410,
            310,
            280
        ]
    },
    {
        "id": 138,
        "box_code": "2297628725581",
        "sequence": 34,
        "dimension": [
            350,
            250,
            100
        ]
    },
    {
        "id": 139,
        "box_code": "8870733378798",
        "sequence": 40,
        "dimension": [
            350,
            250,
            100
        ]
    },
    {
        "id": 140,
        "box_code": "4040479724817",
        "sequence": 28,
        "dimension": [
            340,
            350,
            210
        ]
    },
    {
        "id": 141,
        "box_code": "1484578858023",
        "sequence": 4,
        "dimension": [
            410,
            310,
            280
        ]
    },
    {
        "id": 142,
        "box_code": "4409639128240",
        "sequence": 12,
        "dimension": [
            410,
            310,
            280
        ]
    },
    {
        "id": 143,
        "box_code": "1120605569393",
        "sequence": 24,
        "dimension": [
            480,
            380,
            340
        ]
    },
    {
        "id": 144,
        "box_code": "588013506208",
        "sequence": 27,
        "dimension": [
            340,
            350,
            210
        ]
    },
    {
        "id": 145,
        "box_code": "2328836266567",
        "sequence": 32,
        "dimension": [
            270,
            100,
            150
        ]
    },
    {
        "id": 146,
        "box_code": "3103153170075",
        "sequence": 5,
        "dimension": [
            350,
            250,
            100
        ]
    },
    {
        "id": 147,
        "box_code": "6799252064621",
        "sequence": 25,
        "dimension": [
            350,
            250,
            100
        ]
    },
    {
        "id": 148,
        "box_code": "4339737295166",
        "sequence": 25,
        "dimension": [
            270,
            100,
            150
        ]
    },
    {
        "id": 149,
        "box_code": "8241277363638",
        "sequence": 9,
        "dimension": [
            340,
            350,
            210
        ]
    },
    {
        "id": 150,
        "box_code": "9134458780731",
        "sequence": 30,
        "dimension": [
            480,
            380,
            340
        ]
    },
    {
        "id": 151,
        "box_code": "5894373462279",
        "sequence": 13,
        "dimension": [
            410,
            310,
            280
        ]
    },
    {
        "id": 152,
        "box_code": "6157381344493",
        "sequence": 29,
        "dimension": [
            270,
            100,
            150
        ]
    },
    {
        "id": 153,
        "box_code": "5347969857177",
        "sequence": 9,
        "dimension": [
            480,
            380,
            340
        ]
    },
    {
        "id": 154,
        "box_code": "1832444072541",
        "sequence": 19,
        "dimension": [
            340,
            350,
            210
        ]
    },
    {
        "id": 155,
        "box_code": "3518018833801",
        "sequence": 15,
        "dimension": [
            480,
            380,
            340
        ]
    },
    {
        "id": 156,
        "box_code": "2649712593679",
        "sequence": 5,
        "dimension": [
            480,
            380,
            340
        ]
    },
    {
        "id": 157,
        "box_code": "1499789995954",
        "sequence": 25,
        "dimension": [
            350,
            250,
            100
        ]
    },
    {
        "id": 158,
        "box_code": "4050369822118",
        "sequence": 16,
        "dimension": [
            270,
            100,
            150
        ]
    },
    {
        "id": 159,
        "box_code": "5078940905996",
        "sequence": 16,
        "dimension": [
            270,
            100,
            150
        ]
    },
    {
        "id": 160,
        "box_code": "5958350592196",
        "sequence": 37,
        "dimension": [
            480,
            380,
            340
        ]
    },
    {
        "id": 161,
        "box_code": "6637093428289",
        "sequence": 29,
        "dimension": [
            410,
            310,
            280
        ]
    },
    {
        "id": 162,
        "box_code": "9853302181121",
        "sequence": 1,
        "dimension": [
            340,
            350,
            210
        ]
    },
    {
        "id": 163,
        "box_code": "8686437476855",
        "sequence": 14,
        "dimension": [
            480,
            380,
            340
        ]
    },
    {
        "id": 164,
        "box_code": "8449612521019",
        "sequence": 35,
        "dimension": [
            480,
            380,
            340
        ]
    },
    {
        "id": 165,
        "box_code": "5432879831329",
        "sequence": 15,
        "dimension": [
            410,
            310,
            280
        ]
    },
    {
        "id": 166,
        "box_code": "6416884924019",
        "sequence": 25,
        "dimension": [
            480,
            380,
            340
        ]
    },
    {
        "id": 167,
        "box_code": "5956826204681",
        "sequence": 25,
        "dimension": [
            480,
            380,
            340
        ]
    },
    {
        "id": 168,
        "box_code": "643550337244",
        "sequence": 37,
        "dimension": [
            340,
            350,
            210
        ]
    },
    {
        "id": 169,
        "box_code": "9412666924707",
        "sequence": 36,
        "dimension": [
            410,
            310,
            280
        ]
    },
    {
        "id": 170,
        "box_code": "3062404396817",
        "sequence": 25,
        "dimension": [
            410,
            310,
            280
        ]
    },
    {
        "id": 171,
        "box_code": "3285912882513",
        "sequence": 34,
        "dimension": [
            350,
            250,
            100
        ]
    },
    {
        "id": 172,
        "box_code": "4786463261392",
        "sequence": 25,
        "dimension": [
            410,
            310,
            280
        ]
    },
    {
        "id": 173,
        "box_code": "5732784246711",
        "sequence": 29,
        "dimension": [
            350,
            250,
            100
        ]
    },
    {
        "id": 174,
        "box_code": "1063853755866",
        "sequence": 3,
        "dimension": [
            340,
            350,
            210
        ]
    },
    {
        "id": 175,
        "box_code": "392419288137",
        "sequence": 8,
        "dimension": [
            270,
            100,
            150
        ]
    },
    {
        "id": 176,
        "box_code": "5034979145291",
        "sequence": 28,
        "dimension": [
            340,
            350,
            210
        ]
    },
    {
        "id": 177,
        "box_code": "8474378725149",
        "sequence": 39,
        "dimension": [
            270,
            100,
            150
        ]
    },
    {
        "id": 178,
        "box_code": "1551919533500",
        "sequence": 21,
        "dimension": [
            410,
            310,
            280
        ]
    },
    {
        "id": 179,
        "box_code": "7391079719122",
        "sequence": 13,
        "dimension": [
            340,
            350,
            210
        ]
    },
    {
        "id": 180,
        "box_code": "8856650002150",
        "sequence": 25,
        "dimension": [
            270,
            100,
            150
        ]
    },
    {
        "id": 181,
        "box_code": "2436757274119",
        "sequence": 11,
        "dimension": [
            410,
            310,
            280
        ]
    },
    {
        "id": 182,
        "box_code": "6011909317738",
        "sequence": 3,
        "dimension": [
            480,
            380,
            340
        ]
    },
    {
        "id": 183,
        "box_code": "9585495191306",
        "sequence": 12,
        "dimension": [
            410,
            310,
            280
        ]
    },
    {
        "id": 184,
        "box_code": "3047081931030",
        "sequence": 29,
        "dimension": [
            270,
            100,
            150
        ]
    },
    {
        "id": 185,
        "box_code": "6044810036959",
        "sequence": 6,
        "dimension": [
            350,
            250,
            100
        ]
    },
    {
        "id": 186,
        "box_code": "3086459270891",
        "sequence": 25,
        "dimension": [
            410,
            310,
            280
        ]
    },
    {
        "id": 187,
        "box_code": "6633279549211",
        "sequence": 37,
        "dimension": [
            410,
            310,
            280
        ]
    },
    {
        "id": 188,
        "box_code": "5144038383932",
        "sequence": 29,
        "dimension": [
            340,
            350,
            210
        ]
    },
    {
        "id": 189,
        "box_code": "7740206883006",
        "sequence": 24,
        "dimension": [
            480,
            380,
            340
        ]
    },
    {
        "id": 190,
        "box_code": "1239636588349",
        "sequence": 25,
        "dimension": [
            340,
            350,
            210
        ]
    },
    {
        "id": 191,
        "box_code": "1910996011757",
        "sequence": 8,
        "dimension": [
            340,
            350,
            210
        ]
    },
    {
        "id": 192,
        "box_code": "5698717219336",
        "sequence": 11,
        "dimension": [
            410,
            310,
            280
        ]
    },
    {
        "id": 193,
        "box_code": "3894664049751",
        "sequence": 14,
        "dimension": [
            270,
            100,
            150
        ]
    },
    {
        "id": 194,
        "box_code": "5007681954412",
        "sequence": 35,
        "dimension": [
            410,
            310,
            280
        ]
    },
    {
        "id": 195,
        "box_code": "6457090412056",
        "sequence": 29,
        "dimension": [
            410,
            310,
            280
        ]
    },
    {
        "id": 196,
        "box_code": "8987952743643",
        "sequence": 18,
        "dimension": [
            340,
            350,
            210
        ]
    },
    {
        "id": 197,
        "box_code": "3303939820347",
        "sequence": 6,
        "dimension": [
            270,
            100,
            150
        ]
    },
    {
        "id": 198,
        "box_code": "3085190214666",
        "sequence": 20,
        "dimension": [
            340,
            350,
            210
        ]
    },
    {
        "id": 199,
        "box_code": "5366017189018",
        "sequence": 24,
        "dimension": [
            340,
            350,
            210
        ]
    },
    {
        "id": 200,
        "box_code": "5195900174569",
        "sequence": 2,
        "dimension": [
            480,
            380,
            340
        ]
    }
]